Workbook

Sheet Summary
A1: Topic | B1: What we are proposing | C1: Why / how to say it
A2: Client | B2: Acebet: US sweepstakes / social casino operator, Cyprus entity. Contact: Boris (co-founder). | C2: Referred by Coinflow. First call 27-Oct-2026.
A3: What they want | B3: Split volume across several acquirers by fixed percentages, cascade declines, add acquirers fast. | C3: Leverage on price and redundancy. Approval on Breeze is already in the 90s, so this is not an uplift sale.
A4: Volume basis | B4: About 680,000 successful transactions a month, average ticket about $33. | C4: Real last 30 days: 678,498 deposits, $22.77M, all on Breeze (internal data; never cite it to the client). Boris said ~700K and ~$25M.
A5: Pricing structure | B5: Platform fee $10,000/month flat + a rate per successful transaction in 4 tranches. | C5: Tranche (ladder) pricing: each tranche billed at its own rate within the month, so the average falls as volume grows.
A6: Tranches | B6: 0 to 500,000: $0.030 / 500,001 to 1,000,000: $0.025 / 1,000,001 to 2,000,000: $0.020 / above 2,000,000: $0.015 | C6: Rates per German (27-Oct): 3, 2.5, 2 and 1.5 cents, platform fee on top. Top tranche sits at Spreedly's quoted ~1.5 cents.
A7: Today's bill | B7: See tab Calculator: $19,500 usage + $10,000 platform = $29,500 a month ($354,000 a year). | C7: Average $0.0287 per transaction before the platform fee; $0.0434 all-in.
A8: Billing rules | B8: Charged only on approved transactions. A retried or cascaded payment counts once. Declines cost nothing. No setup fee. | C8: Matches what was promised on the call (retries charged once when accepted).
A9: Included | B9: Orchestration and rules engine; volume split, cascading, retries; monitors and failover; hosted fields, SDKs, sandbox; new provider connections maintained by Yuno; dashboard and insights; KAM, TAM, solutions engineer. | C9: "Every acquirer you add is a routing change, not a new fee."
A10: Not included (pending review) | B10: Reconciliation across Breeze, Coinflow, Whop and Checkout, for further review. | C10: Boris showed interest in reconciliation; scope and price later. Payouts removed from the proposal.
A11: Terms | B11: 36-month contract. Rates locked, tranches reviewed annually. Pricing valid 30 days, subject to final agreement. | C11: Minimums and billing start date not stated yet.
A12: Competitive frame | B12: PaymentIQ ~$0.04/trx, Spreedly ~$0.015/trx (as quoted by Boris). See tab Vs competitors. | C12: Our usage average ($0.029) sits between them; all-in ($0.043) is about PaymentIQ. Unknown whether their quotes include platform fees: ask.
A13: Open risks (internal) | B13: Pricing approval (Justo + Salesforce). Wallet cascading across MoRs to confirm with Ben Lee. 2-week acquirer SLA not in writing yet. Whop needs a provider ticket. Legal check on Cyprus entity. | C13: Policy floor is $0.01 per transaction; every tranche is above it (lowest $0.015).

Sheet Calculator
A1: Input | B1: Value
A2: Successful transactions / month (edit) | B2: 680000
A3: Platform fee / month | B3: 10000
A5: Tranche | B5: From | C5: To | D5: Rate / trx | E5: Trx in tranche | F5: Cost / month
A6: Tranche 1 | B6: 0 | C6: 500000 | D6: 0.03 | E6: =MAX(0,MIN($B$2,500000)-0) | F6: =E6*D6
A7: Tranche 2 | B7: 500001 | C7: 1000000 | D7: 0.025 | E7: =MAX(0,MIN($B$2,1000000)-500000) | F7: =E7*D7
A8: Tranche 3 | B8: 1000001 | C8: 2000000 | D8: 0.02 | E8: =MAX(0,MIN($B$2,2000000)-1000000) | F8: =E8*D8
A9: Tranche 4 | B9: 2000001 | C9: no cap | D9: 0.015 | E9: =MAX(0,$B$2-2000000) | F9: =E9*D9
A11: Usage subtotal | E11: =SUM(E6:E9) | F11: =SUM(F6:F9)
A12: Platform fee | F12: =B3
A13: Total / month | F13: =F11+F12
A14: Total / year | F14: =F13*12
A15: Average usage rate / trx (before platform fee) | F15: =F11/B2
A16: All-in rate / trx (with platform fee) | F16: =F13/B2
A18: Yellow cells are inputs: change the volume or a rate and every number updates.

Sheet Growth
A1: Monthly transactions | B1: Usage / month | C1: Platform fee | D1: Total / month | E1: Usage avg / trx | F1: All-in / trx
A2: 680000 | B2: =MAX(0,MIN(A2,500000)-0)*0.03+MAX(0,MIN(A2,1000000)-500000)*0.025+MAX(0,MIN(A2,2000000)-1000000)*0.02+MAX(0,A2-2000000)*0.015 | C2: =Calculator!$B$3 | D2: =B2+C2 | E2: =B2/A2 | F2: =D2/A2
A3: 1000000 | B3: =MAX(0,MIN(A3,500000)-0)*0.03+MAX(0,MIN(A3,1000000)-500000)*0.025+MAX(0,MIN(A3,2000000)-1000000)*0.02+MAX(0,A3-2000000)*0.015 | C3: =Calculator!$B$3 | D3: =B3+C3 | E3: =B3/A3 | F3: =D3/A3
A4: 1500000 | B4: =MAX(0,MIN(A4,500000)-0)*0.03+MAX(0,MIN(A4,1000000)-500000)*0.025+MAX(0,MIN(A4,2000000)-1000000)*0.02+MAX(0,A4-2000000)*0.015 | C4: =Calculator!$B$3 | D4: =B4+C4 | E4: =B4/A4 | F4: =D4/A4
A5: 2000000 | B5: =MAX(0,MIN(A5,500000)-0)*0.03+MAX(0,MIN(A5,1000000)-500000)*0.025+MAX(0,MIN(A5,2000000)-1000000)*0.02+MAX(0,A5-2000000)*0.015 | C5: =Calculator!$B$3 | D5: =B5+C5 | E5: =B5/A5 | F5: =D5/A5
A6: 3000000 | B6: =MAX(0,MIN(A6,500000)-0)*0.03+MAX(0,MIN(A6,1000000)-500000)*0.025+MAX(0,MIN(A6,2000000)-1000000)*0.02+MAX(0,A6-2000000)*0.015 | C6: =Calculator!$B$3 | D6: =B6+C6 | E6: =B6/A6 | F6: =D6/A6
A8: Volumes above today are illustrative (expansion to Canada, Australia, France, Spain), not forecasts.

Sheet Vs competitors
A1: Option | B1: Rate / trx | C1: Cost / month | D1: Cost / year | E1: Note
A2: Spreedly (quoted) | B2: 0.015 | C2: =B2*Calculator!$B$2 | D2: =C2*12 | E2: As quoted by Boris; unknown if a platform fee applies on top.
A3: Yuno usage only | B3: =Calculator!F15 | C3: =Calculator!F11 | D3: =C3*12 | E3: Tranche usage before the platform fee.
A4: Yuno all-in | B4: =Calculator!F16 | C4: =Calculator!F13 | D4: =C4*12 | E4: Usage plus the $10,000 platform fee.
A5: PaymentIQ (quoted) | B5: 0.04 | C5: =B5*Calculator!$B$2 | D5: =C5*12 | E5: As quoted by Boris; unknown if a platform fee applies on top.
A7: Ask Boris whether the PaymentIQ and Spreedly quotes are all-in; the comparison changes if they carry platform fees.
